gemini/__init__.py
gemini/gemini.py
gemini_library-1.0.0.dist-info/METADATA
gemini_library-1.0.0.dist-info/WHEEL
gemini_library-1.0.0.dist-info/top_level.txt
gemini_library-1.0.0.dist-info/RECORD
