Metadata-Version: 2.4
Name: gemini-library
Version: 1.0.0
Summary: Gemini API response handler with Markdown to HTML conversion
Home-page: 
Author: Test
Author-email: test.email@example.com
Requires-Python: >=3.7
Requires-Dist: google-generativeai
Requires-Dist: markdown
Requires-Dist: beautifulsoup4
Dynamic: author
Dynamic: author-email
Dynamic: description
Dynamic: description-content-type
Dynamic: requires-dist
Dynamic: requires-python
Dynamic: summary
